py_cpu-0.1.2.dist-info/WHEEL
py_cpu-0.1.2.dist-info/LICENSE
py_cpu-0.1.2.dist-info/RECORD
py_cpu-0.1.2.dist-info/top_level.txt
py_cpu-0.1.2.dist-info/METADATA
py_cpu/__init__.py
py_cpu/bindings.cpython-37m-x86_64-linux-gnu.so
py_cpu/bin/list_cpu_features
py_cpu/include/cpu_features/cpu_features_cache_info.h
py_cpu/include/cpu_features/cpuinfo_x86.h
py_cpu/include/cpu_features/cpu_features_macros.h
py_cpu/lib64/libcpu_features.a
py_cpu/lib64/cmake/CpuFeatures/CpuFeaturesTargets-release.cmake
py_cpu/lib64/cmake/CpuFeatures/CpuFeaturesConfigVersion.cmake
py_cpu/lib64/cmake/CpuFeatures/CpuFeaturesTargets.cmake
py_cpu/lib64/cmake/CpuFeatures/CpuFeaturesConfig.cmake
