Metadata-Version: 2.1
Name: py_cpu
Version: 0.1.2
Summary: Python bindings for Google's cpu_features library.
Home-page: https://github.com/Narasimha1997/py_cpu.git
Author: Narasimha Prasanna HN
Author-email: narasimhaprasannahn@gmail.com
License: Apache 2.0 License
Platform: UNKNOWN
Classifier: Development Status :: 4 - Beta
Classifier: Intended Audience :: Developers
Classifier: Topic :: System :: Hardware
Classifier: License :: OSI Approved :: Apache Software License
Classifier: Programming Language :: Python :: 3
Classifier: Programming Language :: Python :: 3.2
Classifier: Programming Language :: Python :: 3.4
Classifier: Programming Language :: Python :: 3.5
Classifier: Programming Language :: Python :: 3.6
Classifier: Programming Language :: Python :: 3.9
Requires-Python: >=3
